LICENSE
README.md
setup.py
pytorus.egg-info/PKG-INFO
pytorus.egg-info/SOURCES.txt
pytorus.egg-info/dependency_links.txt
pytorus.egg-info/entry_points.txt
pytorus.egg-info/requires.txt
pytorus.egg-info/top_level.txt
scripts/__init__.py
scripts/torus.py
torus/__init__.py
torus/schema/__init__.py
torus/schema/reference.py
torus/schema/tests/__init__.py
torus/schema/tests/test_reference.py