Metadata-Version: 2.1
Name: pytorus
Version: 0.0.3
Summary: TOpic Reference Unified Schema, a Python Implementation
Home-page: https://github.com/JWKennington/torus
Author: J. W. Kennington
Author-email: jameswkennington@gmail.com
Project-URL: Bug Reports, https://github.com/JWKennington/torus/issues
Project-URL: Funding, https://www.buymeacoffee.com/locallytrivial
Project-URL: Source, https://github.com/JWKennington/torus
Project-URL: Documentation, https://torus.readthedocs.io/en/latest/
Keywords: topic reference,bibliography,education,reference index
Classifier: Development Status :: 3 - Alpha
Classifier: License :: OSI Approved :: MIT License
Classifier: Programming Language :: Python :: 3
Classifier: Programming Language :: Python :: 3.7
Classifier: Programming Language :: Python :: 3.8
Classifier: Programming Language :: Python :: 3.9
Classifier: Programming Language :: Python :: 3.10
Classifier: Programming Language :: Python :: 3.11
Classifier: Programming Language :: Python :: 3 :: Only
Requires-Python: >=3.7, <4
License-File: LICENSE
Requires-Dist: pyyaml
Provides-Extra: dev
Requires-Dist: check-manifest; extra == "dev"
Provides-Extra: test
Requires-Dist: pytest; extra == "test"
Requires-Dist: pytest-cov; extra == "test"
